dadi_cli/BestFit.py
dadi_cli/GenerateCache.py
dadi_cli/GenerateFs.py
dadi_cli/InferDFE.py
dadi_cli/InferDM.py
dadi_cli/Models.py
dadi_cli/Pdfs.py
dadi_cli/Plot.py
dadi_cli/SimulateFs.py
dadi_cli/Stat.py
dadi_cli/__init__.py
dadi_cli/__main__.py
dadi_cli/conftest.py
dadi_cli/utilities.py
project_cli_ab3nzac1yc_hatch-1.0.3.dist-info/METADATA
project_cli_ab3nzac1yc_hatch-1.0.3.dist-info/WHEEL
project_cli_ab3nzac1yc_hatch-1.0.3.dist-info/entry_points.txt
project_cli_ab3nzac1yc_hatch-1.0.3.dist-info/licenses/LICENSE
project_cli_ab3nzac1yc_hatch-1.0.3.dist-info/RECORD
