Metadata-Version: 2.1
Name: project-cli-AB3NzaC1yc-hatch
Version: 1.0.3
Summary: A command line interface for dadi
Project-URL: Homepage, https://github.com/xin-huang/dadi-cli
Author-email: Xin Huang <xinhuang.res@gmail.com>
License-File: LICENSE
Classifier: License :: OSI Approved :: Apache Software License
Classifier: Programming Language :: Python
Classifier: Programming Language :: Python :: 3
Requires-Dist: project-base-ab3nzac1yc-setuptools
